tensorflow_graphics/__init__.py
tensorflow_graphics/datasets/__init__.py
tensorflow_graphics/datasets/features/__init__.py
tensorflow_graphics/datasets/features/trimesh_feature.py
tensorflow_graphics/datasets/features/trimesh_feature_test.py
tensorflow_graphics/datasets/modelnet40/__init__.py
tensorflow_graphics/datasets/modelnet40/modelnet40_checksums.py
tensorflow_graphics/datasets/modelnet40/modelnet40_makefakes.py
tensorflow_graphics/datasets/modelnet40/modelnet40_run.py
tensorflow_graphics/datasets/modelnet40/modelnet40_show.py
tensorflow_graphics/datasets/modelnet40/modelnet40_test.py
tensorflow_graphics/datasets/shapenet/__init__.py
tensorflow_graphics/datasets/shapenet/shapenet.py
tensorflow_graphics/datasets/shapenet/shapenet_test.py
tensorflow_graphics/datasets/testing/__init__.py
tensorflow_graphics/geometry/__init__.py
tensorflow_graphics/geometry/convolution/__init__.py
tensorflow_graphics/geometry/convolution/graph_convolution.py
tensorflow_graphics/geometry/convolution/graph_pooling.py
tensorflow_graphics/geometry/convolution/utils.py
tensorflow_graphics/geometry/convolution/tests/__init__.py
tensorflow_graphics/geometry/convolution/tests/graph_convolution_test.py
tensorflow_graphics/geometry/convolution/tests/graph_pooling_test.py
tensorflow_graphics/geometry/convolution/tests/utils_test.py
tensorflow_graphics/geometry/deformation_energy/__init__.py
tensorflow_graphics/geometry/deformation_energy/as_conformal_as_possible.py
tensorflow_graphics/geometry/deformation_energy/tests/__init__.py
tensorflow_graphics/geometry/deformation_energy/tests/as_conformal_as_possible_test.py
tensorflow_graphics/geometry/representation/__init__.py
tensorflow_graphics/geometry/representation/grid.py
tensorflow_graphics/geometry/representation/point.py
tensorflow_graphics/geometry/representation/ray.py
tensorflow_graphics/geometry/representation/triangle.py
tensorflow_graphics/geometry/representation/mesh/__init__.py
yifeif_tensorflow_graphics-2020.6.11.dist-info/LICENSE
yifeif_tensorflow_graphics-2020.6.11.dist-info/METADATA
yifeif_tensorflow_graphics-2020.6.11.dist-info/WHEEL
yifeif_tensorflow_graphics-2020.6.11.dist-info/top_level.txt
yifeif_tensorflow_graphics-2020.6.11.dist-info/RECORD
